common_fn_chunk/__about__.py
common_fn_chunk/__init__.py
common_fn_chunk-0.0.2.dist-info/METADATA
common_fn_chunk-0.0.2.dist-info/WHEEL
common_fn_chunk-0.0.2.dist-info/licenses/LICENSE.txt
common_fn_chunk-0.0.2.dist-info/RECORD
